Neural_Network.py
Neuron.py
Sigmoid_Neuron.py
feedforwardnet_shine7-0.0.4.dist-info/LICENSE.txt
feedforwardnet_shine7-0.0.4.dist-info/METADATA
feedforwardnet_shine7-0.0.4.dist-info/WHEEL
feedforwardnet_shine7-0.0.4.dist-info/top_level.txt
feedforwardnet_shine7-0.0.4.dist-info/RECORD
