Metadata-Version: 2.1
Name: feedforwardnet-shine7
Version: 0.0.4
Summary: Feed Forward Neural Networks
Home-page: https://github.com/Subhash3/Neural-Networks/tree/master/Feed_Forward_Networks
Author: Subhash Sarangi
Author-email: subhashsarangi123@gmail.com
License: UNKNOWN
Platform: UNKNOWN
Classifier: Programming Language :: Python :: 3
Classifier: Programming Language :: Python :: 3.6
Classifier: Programming Language :: Python :: 3.7
Classifier: Operating System :: OS Independent
